subframe/__init__.py
subframe/datatables.py
subframe/encoder.py
subframe/error.py
subframe/pivot.py
subframe/plugin.py
subframe/subframe.py
subframe/static/c3/LICENSE
subframe/static/c3/css/c3.min.css
subframe/static/c3/js/c3.min.js
subframe/static/d3/LICENSE
subframe/static/d3/js/d3.min.js
subframe/static/datatables/license.txt
subframe/static/datatables/css/jquery.dataTables.min.css
subframe/static/datatables/images/sort_asc.png
subframe/static/datatables/images/sort_asc_disabled.png
subframe/static/datatables/images/sort_both.png
subframe/static/datatables/images/sort_desc.png
subframe/static/datatables/images/sort_desc_disabled.png
subframe/static/datatables/js/jquery.dataTables.min.js
subframe/static/pivot/LICENSE.md
subframe/static/pivot/css/pivot.min.css
subframe/static/pivot/js/c3_renderers.min.js
subframe/static/pivot/js/d3_renderers.min.js
subframe/static/pivot/js/export_renderers.min.js
subframe/static/pivot/js/gchart_renderers.min.js
subframe/static/pivot/js/pivot.es.min.js
subframe/static/pivot/js/pivot.fr.min.js
subframe/static/pivot/js/pivot.min.js
subframe/static/pivot/js/pivot.pt.min.js
subframe/static/pivot/js/pivot.tr.min.js
subframe-0.0.1.dist-info/DESCRIPTION.rst
subframe-0.0.1.dist-info/METADATA
subframe-0.0.1.dist-info/metadata.json
subframe-0.0.1.dist-info/pbr.json
subframe-0.0.1.dist-info/RECORD
subframe-0.0.1.dist-info/top_level.txt
subframe-0.0.1.dist-info/WHEEL
subframe-0.0.1.dist-info/zip-safe
