Metadata-Version: 2.0
Name: subframe
Version: 0.0.1
Summary: Jupyter-Pandas DataFrame integration and visualisation
Home-page: https://github.com/joshbode/subframe
Author: Josh Bode
Author-email: joshbode@fastmail.com
License: MIT
Keywords: ipython,notebook,dataframe
Platform: UNKNOWN
Classifier: Development Status :: 3 - Alpha
Classifier: Framework :: IPython
Classifier: License :: OSI Approved :: MIT License
Classifier: Programming Language :: Python :: 2
Classifier: Programming Language :: Python :: 3
Classifier: Topic :: Scientific/Engineering :: Visualization
Requires-Dist: ipython
Requires-Dist: notebook
Requires-Dist: pandas
